PyIRC/numerics.py
PyIRC/line.py
PyIRC/casemapping.py
PyIRC/__init__.py
PyIRC/auxparse.py
PyIRC/signal.py
PyIRC/base.py
PyIRC/formatting/__init__.py
PyIRC/formatting/colours.py
PyIRC/formatting/formatters.py
PyIRC/formatting/pprint.py
PyIRC/extensions/__init__.py
PyIRC/extensions/sasl.py
PyIRC/extensions/cap.py
PyIRC/extensions/autojoin.py
PyIRC/extensions/kickrejoin.py
PyIRC/extensions/bantrack.py
PyIRC/extensions/basetrack.py
PyIRC/extensions/isupport.py
PyIRC/extensions/services.py
PyIRC/extensions/starttls.py
PyIRC/extensions/basicrfc.py
PyIRC/extensions/altnick.py
PyIRC/extensions/lag.py
PyIRC/extensions/basicapi.py
PyIRC/extensions/channeltrack.py
PyIRC/extensions/ctcp.py
PyIRC/extensions/usertrack.py
PyIRC/extensions/ircd/inspircd.py
PyIRC/extensions/ircd/hybridfamily.py
PyIRC/extensions/ircd/__init__.py
PyIRC/extensions/ircd/base.py
PyIRC/util/__init__.py
PyIRC/util/enum.py
PyIRC/util/classutil.py
PyIRC/util/version.py
PyIRC/io/__init__.py
PyIRC/io/null.py
PyIRC/io/socket.py
PyIRC/io/eventlet.py
PyIRC/io/asyncio.py
PyIRC-3.0b1.dist-info/top_level.txt
PyIRC-3.0b1.dist-info/METADATA
PyIRC-3.0b1.dist-info/DESCRIPTION.rst
PyIRC-3.0b1.dist-info/metadata.json
PyIRC-3.0b1.dist-info/WHEEL
PyIRC-3.0b1.dist-info/RECORD
