Metadata-Version: 2.0
Name: PyIRC
Version: 3.0b1
Summary: A Python IRC library
Home-page: https://foxkit-us.github.io/PyIRC
Author: foxkit.us development group
Author-email: elizabeth@interlinked.me
License: UNKNOWN
Keywords: IRC chat development
Platform: UNKNOWN
Classifier: Development Status :: 3 - Alpha
Classifier: Intended Audience :: Developers
Classifier: Topic :: Communications :: Chat :: Internet Relay Chat
Classifier: Topic :: Internet
Classifier: Topic :: Software Development :: Libraries :: Python Modules
Classifier: Programming Language :: Python :: 3 :: Only
Classifier: Programming Language :: Python :: 3.3
Classifier: Programming Language :: Python :: 3.4
Classifier: Operating System :: OS Independent
Classifier: License :: DFSG approved
Requires-Dist: taillight (>=0.2b3)
